tests/sim/counter.sv
// Counter module in SystemVerilog (hand-written for comparison)

module counter (
    input  wire       clk,
    input  wire       reset,
    input  wire       enable,
    output logic [7:0] count
);

    logic [7:0] count_reg;

    always_ff @(posedge clk) begin
        if (reset) begin
            count_reg <= 8'b0;
        end else if (enable) begin
            count_reg <= count_reg + 1;
        end
    end

    assign count = count_reg;

endmodule

tests/sim/counter.vcd
$version Generated by VerilatedVcd $end
$timescale 1ps $end
 $scope module TOP $end
  $var wire 1 # clk $end
  $var wire 1 $ reset $end
  $var wire 1 % enable $end
  $var wire 8 & count [7:0] $end
  $scope module counter $end
   $var wire 1 # clk $end
   $var wire 1 $ reset $end
   $var wire 1 % enable $end
   $var wire 8 & count [7:0] $end
   $var wire 8 ' count_reg [7:0] $end
  $upscope $end
 $upscope $end
$enddefinitions $end


#0
1#
1$
0%
b00000000 &
b00000000 '
#1
0#
#2
1#
#3
0#
#4
1#
#5
0#
#6
1#
#7
0#
#8
1#
#9
0#
#10
1#
#11
0#
#12
1#
#13
0#
#14
1#
#15
0#
#16
1#
#17
0#
#18
1#
#19
0#
#20
1#
0$
#21
0#
#22
1#
#23
0#
#24
1#
#25
0#
#26
1#
#27
0#
#28
1#
#29
0#
#30
1#
1%
b00000001 &
b00000001 '
#31
0#
#32
1#
b00000010 &
b00000010 '
#33
0#
#34
1#
b00000011 &
b00000011 '
#35
0#
#36
1#
b00000100 &
b00000100 '
#37
0#
#38
1#
b00000101 &
b00000101 '
#39
0#
#40
1#
b00000110 &
b00000110 '
#41
0#
#42
1#
b00000111 &
b00000111 '
#43
0#
#44
1#
b00001000 &
b00001000 '
#45
0#
#46
1#
b00001001 &
b00001001 '
#47
0#
#48
1#
b00001010 &
b00001010 '
#49
0#
#50
1#
b00001011 &
b00001011 '
#51
0#
#52
1#
b00001100 &
b00001100 '
#53
0#
#54
1#
b00001101 &
b00001101 '
#55
0#
#56
1#
b00001110 &
b00001110 '
#57
0#
#58
1#
b00001111 &
b00001111 '
#59
0#
#60
1#
b00010000 &
b00010000 '
#61
0#
#62
1#
b00010001 &
b00010001 '
#63
0#
#64
1#
b00010010 &
b00010010 '
#65
0#
#66
1#
b00010011 &
b00010011 '
#67
0#
#68
1#
b00010100 &
b00010100 '
#69
0#
#70
1#
b00010101 &
b00010101 '
#71
0#
#72
1#
b00010110 &
b00010110 '
#73
0#
#74
1#
b00010111 &
b00010111 '
#75
0#
#76
1#
b00011000 &
b00011000 '
#77
0#
#78
1#
b00011001 &
b00011001 '
#79
0#
#80
1#
b00011010 &
b00011010 '
#81
0#
#82
1#
b00011011 &
b00011011 '
#83
0#
#84
1#
b00011100 &
b00011100 '
#85
0#
#86
1#
b00011101 &
b00011101 '
#87
0#
#88
1#
b00011110 &
b00011110 '
#89
0#
#90
1#
b00011111 &
b00011111 '
#91
0#
#92
1#
b00100000 &
b00100000 '
#93
0#
#94
1#
b00100001 &
b00100001 '
#95
0#
#96
1#
b00100010 &
b00100010 '
#97
0#
#98
1#
b00100011 &
b00100011 '
#99
0#
#100
1#
b00100100 &
b00100100 '
#101
0#
#102
1#
b00100101 &
b00100101 '
#103
0#
#104
1#
b00100110 &
b00100110 '
#105
0#
#106
1#
b00100111 &
b00100111 '
#107
0#
#108
1#
b00101000 &
b00101000 '
#109
0#
#110
1#
b00101001 &
b00101001 '
#111
0#
#112
1#
b00101010 &
b00101010 '
#113
0#
#114
1#
b00101011 &
b00101011 '
#115
0#
#116
1#
b00101100 &
b00101100 '
#117
0#
#118
1#
b00101101 &
b00101101 '
#119
0#
#120
1#
b00101110 &
b00101110 '
#121
0#
#122
1#
b00101111 &
b00101111 '
#123
0#
#124
1#
b00110000 &
b00110000 '
#125
0#
#126
1#
b00110001 &
b00110001 '
#127
0#
#128
1#
b00110010 &
b00110010 '
#129
0#
#130
1#
b00110011 &
b00110011 '
#131
0#
#132
1#
b00110100 &
b00110100 '
#133
0#
#134
1#
b00110101 &
b00110101 '
#135
0#
#136
1#
b00110110 &
b00110110 '
#137
0#
#138
1#
b00110111 &
b00110111 '
#139
0#
#140
1#
b00111000 &
b00111000 '
#141
0#
#142
1#
b00111001 &
b00111001 '
#143
0#
#144
1#
b00111010 &
b00111010 '
#145
0#
#146
1#
b00111011 &
b00111011 '
#147
0#
#148
1#
b00111100 &
b00111100 '
#149
0#
#150
1#
b00111101 &
b00111101 '
#151
0#
#152
1#
b00111110 &
b00111110 '
#153
0#
#154
1#
b00111111 &
b00111111 '
#155
0#
#156
1#
b01000000 &
b01000000 '
#157
0#
#158
1#
b01000001 &
b01000001 '
#159
0#
#160
1#
b01000010 &
b01000010 '
#161
0#
#162
1#
b01000011 &
b01000011 '
#163
0#
#164
1#
b01000100 &
b01000100 '
#165
0#
#166
1#
b01000101 &
b01000101 '
#167
0#
#168
1#
b01000110 &
b01000110 '
#169
0#
#170
1#
b01000111 &
b01000111 '
#171
0#
#172
1#
b01001000 &
b01001000 '
#173
0#
#174
1#
b01001001 &
b01001001 '
#175
0#
#176
1#
b01001010 &
b01001010 '
#177
0#
#178
1#
b01001011 &
b01001011 '
#179
0#
#180
1#
b01001100 &
b01001100 '
#181
0#
#182
1#
b01001101 &
b01001101 '
#183
0#
#184
1#
b01001110 &
b01001110 '
#185
0#
#186
1#
b01001111 &
b01001111 '
#187
0#
#188
1#
b01010000 &
b01010000 '
#189
0#
#190
1#
b01010001 &
b01010001 '
#191
0#
#192
1#
b01010010 &
b01010010 '
#193
0#
#194
1#
b01010011 &
b01010011 '
#195
0#
#196
1#
b01010100 &
b01010100 '
#197
0#
#198
1#
b01010101 &
b01010101 '
#199
0#
#200
1#
0%
